LICENSE.txt
README.md
setup.cfg
setup.py
suav/__init__.py
suav/suav.py
suav.egg-info/PKG-INFO
suav.egg-info/SOURCES.txt
suav.egg-info/dependency_links.txt
suav.egg-info/requires.txt
suav.egg-info/top_level.txt