Metadata-Version: 2.1
Name: suav
Version: 0.2
Summary: suavisa dados para um plot no python
Home-page: https://github.com/raphonon/suav
Download-URL: https://github.com/raphonon/suav/archive/refs/tags/suav_0.2.tar.gz
Author: raphonon
Author-email: rafaelsantod@gmail.com
License: MIT
Keywords: SOME,MEANINGFULL,KEYWORDS
Classifier: Development Status :: 3 - Alpha
Classifier: Intended Audience :: Developers
Classifier: Topic :: Software Development :: Build Tools
Classifier: License :: OSI Approved :: MIT License
Classifier: Programming Language :: Python :: 3
Classifier: Programming Language :: Python :: 3.4
Classifier: Programming Language :: Python :: 3.5
Classifier: Programming Language :: Python :: 3.6
License-File: LICENSE.txt
